kolibri_sync_extras_plugin/__init__.py
kolibri_sync_extras_plugin/kolibri_plugin.py
kolibri_sync_extras_plugin/options.py
kolibri_sync_extras_plugin/tasks.py
kolibri_sync_extras_plugin/management/__init__.py
kolibri_sync_extras_plugin/management/commands/__init__.py
kolibri_sync_extras_plugin/management/commands/sync_proceed_to.py
kolibri_sync_extras_plugin/sync/__init__.py
kolibri_sync_extras_plugin/sync/context.py
kolibri_sync_extras_plugin/sync/operations.py
kolibri_sync_extras_plugin-0.2.2.dist-info/AUTHORS.rst
kolibri_sync_extras_plugin-0.2.2.dist-info/LICENSE
kolibri_sync_extras_plugin-0.2.2.dist-info/METADATA
kolibri_sync_extras_plugin-0.2.2.dist-info/WHEEL
kolibri_sync_extras_plugin-0.2.2.dist-info/entry_points.txt
kolibri_sync_extras_plugin-0.2.2.dist-info/top_level.txt
kolibri_sync_extras_plugin-0.2.2.dist-info/RECORD
