Metadata-Version: 2.1
Name: kolibri-sync-extras-plugin
Version: 0.2.2
Summary: Kolibri plugin that provides extra features for peer-to-peer syncing
Home-page: https://github.com/learningequality/kolibri-sync-extras-plugin
Author: Learning Equality
Author-email: info@learningequality.org
License: MIT
Keywords: kolibri,syncing,morango
Platform: UNKNOWN
Classifier: Development Status :: 4 - Beta
Classifier: Framework :: Django
Classifier: Intended Audience :: Developers
Classifier: License :: OSI Approved :: MIT License
Classifier: Natural Language :: English
Classifier: Programming Language :: Python :: 2
Classifier: Programming Language :: Python :: 2.7
Classifier: Programming Language :: Python :: 3
Classifier: Programming Language :: Python :: 3.4
Classifier: Programming Language :: Python :: 3.5
Classifier: Programming Language :: Python :: 3.6
Classifier: Programming Language :: Python :: 3.7
Classifier: Programming Language :: Python :: 3.8
Classifier: Programming Language :: Python :: 3.9
License-File: LICENSE
License-File: AUTHORS.rst
Provides-Extra: dev
Requires-Dist: setuptools; extra == "dev"
Requires-Dist: wheel; extra == "dev"
Requires-Dist: twine; extra == "dev"
